kng/__init__.py
kng/dt.py
kng/iter.py
kng/pd.py
kng/pypi.py
kng/trade.py
kng-0.6.1.dist-info/LICENSE
kng-0.6.1.dist-info/METADATA
kng-0.6.1.dist-info/WHEEL
kng-0.6.1.dist-info/entry_points.txt
kng-0.6.1.dist-info/RECORD
