Metadata-Version: 2.1
Name: kng
Version: 0.6.1
Summary: handy utility functions collection
Home-page: https://hoishing.github.io/kng
Keywords: utilities
Author: Kelvin Ng
Author-email: hoishing@gmail.com
Requires-Python: >=3.11,<4.0
Classifier: Programming Language :: Python :: 3
Classifier: Programming Language :: Python :: 3.11
Project-URL: Repository, https://github.com/hoishing/kng
